rest_framework_app_api/__init__.py
rest_framework_app_api/exceptions.py
rest_framework_app_api/generics.py
rest_framework_app_api/mixins.py
rest_framework_app_api/pagination.py
rest_framework_app_api/renderers.py
rest_framework_app_api/response.py
rest_framework_app_api/settings.py
rest_framework_app_api/utils.py
rest_framework_app_api/views.py
rest_framework_app_api/viewsets.py
djangorestframework_appapi-0.0.3.dist-info/AUTHORS
djangorestframework_appapi-0.0.3.dist-info/LICENSE
djangorestframework_appapi-0.0.3.dist-info/METADATA
djangorestframework_appapi-0.0.3.dist-info/WHEEL
djangorestframework_appapi-0.0.3.dist-info/top_level.txt
djangorestframework_appapi-0.0.3.dist-info/RECORD
