Metadata-Version: 2.1
Name: djangorestframework-appapi
Version: 0.0.3
Summary: A Django REST framework API adapter for the App(IOS, Andorid, WebApp) API spec.
Home-page: https://github.com/allran/djangorestframework-appapi
Author: Allran.Qu
Author-email: 
License: BSD
Platform: UNKNOWN
Classifier: Development Status :: 5 - Production/Stable
Classifier: Environment :: Web Environment
Classifier: Framework :: Django
Classifier: Intended Audience :: Developers
Classifier: License :: OSI Approved :: BSD License
Classifier: Operating System :: OS Independent
Classifier: Programming Language :: Python
Classifier: Programming Language :: Python :: 3
Classifier: Programming Language :: Python :: 3.5
Classifier: Programming Language :: Python :: 3.6
Classifier: Programming Language :: Python :: 3.7
Classifier: Topic :: Internet :: WWW/HTTP
Classifier: Topic :: Software Development :: Libraries :: Application Frameworks
Classifier: Topic :: Software Development :: Libraries :: Python Modules
Requires-Python: >=3.5
Requires-Dist: djangorestframework (>=3.10)
Requires-Dist: django (>=1.11)
